README.rst
setup.py
loopDB/__init__.py
loopDB/loopDB.py
loopDB/tables.py
loopDB.egg-info/PKG-INFO
loopDB.egg-info/SOURCES.txt
loopDB.egg-info/dependency_links.txt
loopDB.egg-info/requires.txt
loopDB.egg-info/top_level.txt