Metadata-Version: 1.1
Name: loopDB
Version: 0.2
Summary: A module for creating and storing DNA parts for Loop Assembly
Home-page: https://github.com/HaseloffLab/LoopDB
Author: Mihails Delmans
Author-email: md656@cam.ac.uk
License: GPL
Download-URL: https://github.com/HaseloffLab/LoopDB/archive/0.2.tar.gz
Keywords: bioinfomratics parts synthetic biology loop assembly
Platform: UNKNOWN
Classifier: Development Status :: 4 - Beta
Classifier: Intended Audience :: Developers
Classifier: Intended Audience :: Science/Research
Classifier: Topic :: Scientific/Engineering :: Bio-Informatics
Classifier: License :: OSI Approved :: MIT License
Classifier: Programming Language :: Python :: 2.7
